bigsdb/base_application.py
bigsdb/constants.py
bigsdb/data_connector.py
bigsdb/datastore.py
bigsdb/job_manager.py
bigsdb/locus.py
bigsdb/plugin.py
bigsdb/prefstore.py
bigsdb/scheme.py
bigsdb/scheme_selector.py
bigsdb/script.py
bigsdb/utils.py
bigsdb/xml_parser.py
bigsdb-0.0.7.dist-info/licenses/LICENSE
bigsdb-0.0.7.dist-info/METADATA
bigsdb-0.0.7.dist-info/WHEEL
bigsdb-0.0.7.dist-info/top_level.txt
bigsdb-0.0.7.dist-info/RECORD
