Metadata-Version: 2.4
Name: bigsdb
Version: 0.0.7
Summary: BIGSdb Python Toolkit
Author-email: Keith Jolley <keith.jolley@biology.ox.ac.uk>
License:                     GNU GENERAL PUBLIC LICENSE
Project-URL: Homepage, https://github.com/kjolley/BIGSdb_Python_Toolkit
Classifier: License :: OSI Approved :: GNU General Public License v3 or later (GPLv3+)
Classifier: Programming Language :: Python
Classifier: Programming Language :: Python :: 3
Requires-Python: >=3.9
License-File: LICENSE
Requires-Dist: psycopg2>=2.9.9
Requires-Dist: pyuca>=1.2
Requires-Dist: XlsxWriter>=3.2.0
Dynamic: license-file
